mail_paicha_cloud-0.3.1.dist-info/licenses/LICENSE
paichacloud/__init__.py
paichacloud/client.py
mail_paicha_cloud-0.3.1.dist-info/METADATA
mail_paicha_cloud-0.3.1.dist-info/WHEEL
mail_paicha_cloud-0.3.1.dist-info/top_level.txt
mail_paicha_cloud-0.3.1.dist-info/RECORD
