Metadata-Version: 2.4
Name: mail-paicha-cloud
Version: 0.3.1
Summary: Simple Python client for PaichaCloud disposable email API
Author-email: nyaa <nyaa@paicha.cloud>
License: MIT License
Project-URL: Homepage, https://github.com/yukisakuna/mail-paicha-cloud
Project-URL: Source, https://github.com/yukisakuna/mail-paicha-cloud
Requires-Python: >=3.8
License-File: LICENSE
Requires-Dist: requests>=2.25.0
Dynamic: license-file
